py_manage_nginx/__about__.py
py_manage_nginx/__init__.py
py_manage_nginx/hosting.py
py_manage_nginx/manager.py
py_manage_nginx-1.0.0.dist-info/LICENSE.txt
py_manage_nginx-1.0.0.dist-info/METADATA
py_manage_nginx-1.0.0.dist-info/WHEEL
py_manage_nginx-1.0.0.dist-info/top_level.txt
py_manage_nginx-1.0.0.dist-info/RECORD
