Metadata-Version: 2.1
Name: py-manage-nginx
Version: 1.0.0
Summary: Use Python to manage Nginx on the machine.
Author-email: Trương Hải Đăng <haidanghth910@gmail.com>
License: MIT License
Project-URL: Documentation, https://github.com/TruongHaiDang/py-manage-nginx#readme
Project-URL: Issues, https://github.com/TruongHaiDang/py-manage-nginx/issues
Project-URL: Source, https://github.com/TruongHaiDang/py-manage-nginx
Classifier: Development Status :: 4 - Beta
Classifier: Programming Language :: Python
Classifier: Programming Language :: Python :: 3.8
Classifier: Programming Language :: Python :: 3.9
Classifier: Programming Language :: Python :: 3.10
Classifier: Programming Language :: Python :: 3.11
Classifier: Programming Language :: Python :: 3.12
Classifier: Programming Language :: Python :: Implementation :: CPython
Classifier: Programming Language :: Python :: Implementation :: PyPy
Requires-Python: >=3.8
License-File: LICENSE.txt
